limitlessled/__init__.py
limitlessled/bridge.py
limitlessled/pipeline.py
limitlessled/presets.py
limitlessled/util.py
limitlessled/group/__init__.py
limitlessled/group/rgbw.py
limitlessled/group/white.py
limitlessled-1.0.1.dist-info/DESCRIPTION.rst
limitlessled-1.0.1.dist-info/METADATA
limitlessled-1.0.1.dist-info/RECORD
limitlessled-1.0.1.dist-info/WHEEL
limitlessled-1.0.1.dist-info/metadata.json
limitlessled-1.0.1.dist-info/top_level.txt
