Metadata-Version: 2.0
Name: limitlessled
Version: 1.0.1
Summary: Control LimitlessLED products.
Home-page: https://github.com/happyleavesaoc/python-limitlessled/
Author: happyleaves
Author-email: happyleaves.tfr@gmail.com
License: MIT
Platform: UNKNOWN
Classifier: License :: OSI Approved :: MIT License
Classifier: Operating System :: OS Independent
Classifier: Programming Language :: Python :: 3
